LICENSE.txt
MANIFEST.in
README.md
setup.py
./configure.py
./lcd_i2c_printer.py
./main.py
./urbanbus.py
./lib/__init__.py
./lib/lcd_api.py
./lib/pico_i2c_lcd.py
res/config.html
res/error_ssid.html
res/saved.html
res/setup.html
res/css/spectre-exp.min.css
res/css/spectre-icons.min.css
res/css/spectre.min.css
tmp/.gitignore
tmp/tmp_setup.html
waitless_sviz.egg-info/PKG-INFO
waitless_sviz.egg-info/SOURCES.txt
waitless_sviz.egg-info/dependency_links.txt
waitless_sviz.egg-info/top_level.txt